tax_calculator/__init__.py
tax_calculator/calculator.py
tax_calculator_by_yousaf-0.2.3.dist-info/licenses/LICENSE
tax_calculator_by_yousaf-0.2.3.dist-info/METADATA
tax_calculator_by_yousaf-0.2.3.dist-info/WHEEL
tax_calculator_by_yousaf-0.2.3.dist-info/entry_points.txt
tax_calculator_by_yousaf-0.2.3.dist-info/top_level.txt
tax_calculator_by_yousaf-0.2.3.dist-info/RECORD
