Metadata-Version: 2.4
Name: tax_calculator_by_yousaf
Version: 0.2.3
Summary: A simple calculator to compute income tax for India FY 2025-26
Home-page: https://github.com/yousafkhamza/tax_calculator_by_yousaf
Author: Yousaf Khamza
Author-email: yousaf@example.com
Classifier: Programming Language :: Python :: 3
Classifier: License :: OSI Approved :: MIT License
Classifier: Operating System :: OS Independent
Requires-Python: >=3.6
License-File: LICENSE
Dynamic: author
Dynamic: author-email
Dynamic: classifier
Dynamic: description
Dynamic: description-content-type
Dynamic: home-page
Dynamic: license-file
Dynamic: requires-python
Dynamic: summary
